README.txt
httplib.py
setup.py
urllib2.py
httpsproxy_urllib2.egg-info/PKG-INFO
httpsproxy_urllib2.egg-info/SOURCES.txt
httpsproxy_urllib2.egg-info/dependency_links.txt
httpsproxy_urllib2.egg-info/top_level.txt
