Metadata-Version: 1.0
Name: httpsproxy-urllib2
Version: 1.0
Summary: Python 2.5 urllib2 patched to use CONNECT for https proxies
Home-page: http://pypi.python.org/pypi/httpsproxy_urllib2
Author: Jarn AS
Author-email: info@jarn.com
License: Python
Keywords: urllib2 https proxy CONNECT
Platform: UNKNOWN
Classifier: Programming Language :: Python
Classifier: Topic :: Software Development :: Libraries :: Python Modules
